kraken_db/kraken_db.py
kraken_db-0.0.10.dist-info/LICENSE.txt
kraken_db-0.0.10.dist-info/METADATA
kraken_db-0.0.10.dist-info/WHEEL
kraken_db-0.0.10.dist-info/top_level.txt
kraken_db-0.0.10.dist-info/RECORD
